oscer_shopify/__init__.py
oscer_shopify/core.py
oscer_shopify-0.1.0.dist-info/licenses/LICENSE
oscer_shopify-0.1.0.dist-info/METADATA
oscer_shopify-0.1.0.dist-info/WHEEL
oscer_shopify-0.1.0.dist-info/top_level.txt
oscer_shopify-0.1.0.dist-info/RECORD
